{
    "m_Version": 12,
    "DisplayName": "#STR_EXPANSION_MARKET_CATEGORY_HELMETS",
    "Icon": "Deliver",
    "Color": "FBFCFEFF",
    "IsExchange": 0,
    "InitStockPercent": 75.0,
    "Items": [
        {
            "ClassName": "greathelm",
            "MaxPriceThreshold": 1500,
            "MinPriceThreshold": 1500,
            "SellPricePercent": -1.0,
            "MaxStockThreshold": 100,
            "MinStockThreshold": 100,
            "QuantityPercent": -1,
            "SpawnAttachments": [],
            "Variants": []
        },
        {
            "ClassName": "zsh3pilothelmet",
            "MaxPriceThreshold": 500,
            "MinPriceThreshold": 500,
            "SellPricePercent": -1.0,
            "MaxStockThreshold": 100,
            "MinStockThreshold": 100,
            "QuantityPercent": -1,
            "SpawnAttachments": [],
            "Variants": [
                "zsh3pilothelmet_green",
                "zsh3pilothelmet_black"
            ]
        },
        {
            "ClassName": "zsh3pilothelmet_green",
            "MaxPriceThreshold": 500,
            "MinPriceThreshold": 500,
            "SellPricePercent": -1.0,
            "MaxStockThreshold": 100,
            "MinStockThreshold": 100,
            "QuantityPercent": -1,
            "SpawnAttachments": [],
            "Variants": []
        },
        {
            "ClassName": "zsh3pilothelmet_black",
            "MaxPriceThreshold": 500,
            "MinPriceThreshold": 500,
            "SellPricePercent": -1.0,
            "MaxStockThreshold": 100,
            "MinStockThreshold": 100,
            "QuantityPercent": -1,
            "SpawnAttachments": [],
            "Variants": []
        },
        {
            "ClassName": "mich2001helmet",
            "MaxPriceThreshold": 3500,
            "MinPriceThreshold": 3500,
            "SellPricePercent": -1.0,
            "MaxStockThreshold": 100,
            "MinStockThreshold": 100,
            "QuantityPercent": -1,
            "SpawnAttachments": [],
            "Variants": [
                "expansionmich2001desert"
            ]
        },
        {
            "ClassName": "gorkahelmetvisor",
            "MaxPriceThreshold": 100,
            "MinPriceThreshold": 100,
            "SellPricePercent": -1.0,
            "MaxStockThreshold": 100,
            "MinStockThreshold": 100,
            "QuantityPercent": -1,
            "SpawnAttachments": [],
            "Variants": []
        },
        {
            "ClassName": "gorkahelmet",
            "MaxPriceThreshold": 3000,
            "MinPriceThreshold": 3000,
            "SellPricePercent": -1.0,
            "MaxStockThreshold": 100,
            "MinStockThreshold": 100,
            "QuantityPercent": -1,
            "SpawnAttachments": [
                "gorkahelmetvisor"
            ],
            "Variants": [
                "gorkahelmet_black"
            ]
        },
        {
            "ClassName": "ssh68helmet",
            "MaxPriceThreshold": 1000,
            "MinPriceThreshold": 1000,
            "SellPricePercent": -1.0,
            "MaxStockThreshold": 100,
            "MinStockThreshold": 100,
            "QuantityPercent": -1,
            "SpawnAttachments": [],
            "Variants": []
        },
        {
            "ClassName": "ballistichelmet_un",
            "MaxPriceThreshold": 2500,
            "MinPriceThreshold": 2500,
            "SellPricePercent": -1.0,
            "MaxStockThreshold": 100,
            "MinStockThreshold": 100,
            "QuantityPercent": -1,
            "SpawnAttachments": [],
            "Variants": [
                "ballistichelmet_black",
                "ballistichelmet_green"
            ]
        },
        {
            "ClassName": "dzn_GorkaHelmet_White",
            "MaxPriceThreshold": 3500,
            "MinPriceThreshold": 3500,
            "SellPricePercent": -1.0,
            "MaxStockThreshold": 100,
            "MinStockThreshold": 100,
            "QuantityPercent": -1,
            "SpawnAttachments": [
                "gorkahelmetvisor"
            ],
            "Variants": []
        },
        {
            "ClassName": "dzn_BallisticHelmet_White",
            "MaxPriceThreshold": 3000,
            "MinPriceThreshold": 3000,
            "SellPricePercent": -1.0,
            "MaxStockThreshold": 100,
            "MinStockThreshold": 100,
            "QuantityPercent": -1,
            "SpawnAttachments": [],
            "Variants": []
        }
    ]
}